secret/__init__.py
secret/santa.py
xsanta-0.1.3.dist-info/LICENSE
xsanta-0.1.3.dist-info/METADATA
xsanta-0.1.3.dist-info/WHEEL
xsanta-0.1.3.dist-info/top_level.txt
xsanta-0.1.3.dist-info/RECORD
