Metadata-Version: 2.1
Name: xsanta
Version: 0.1.3
Summary: Secret Santa Generator
Home-page: https://github.com/alpha-xone/xsanta
Author: Alpha x1
Author-email: alpha.xone@outlook.com
License: Apache
Platform: UNKNOWN
Classifier: License :: OSI Approved :: Apache Software License
Classifier: Programming Language :: Python :: 3.6
Classifier: Programming Language :: Python :: 3.7
Classifier: Programming Language :: Python :: 3.8
Requires-Dist: fire (>=0.3.1)
